{
    "cyaneaTheme": {
        "primary": "F8BBD0",
        "accent": "A1887F",
        "background": "FFF0F5"
    },
    "cABg": "FFF0F5",
    "cAPrimaryText": "4A4A4A",
    "cARoomText": "4A4A4A",
    "cASecondaryText": "A1887F",
    "cChngBg": "F8BBD0",
    "cChngPrimaryText": "4A4A4A",
    "cChngRoomText": "4A4A4A",
    "cChngSecondaryText": "A1887F",
    "cDivider": "A1887F",
    "cEmptyBg": "FFFFFF",
    "cError": "B00020",
    "cHBg": "FFF0F5",
    "cHPrimaryText": "4A4A4A",
    "cHRoomText": "4A4A4A",
    "cHSecondaryText": "A1887F",
    "cHeaderBg": "F8BBD0",
    "cHeaderPrimaryText": "4A4A4A",
    "cHeaderSecondaryText": "A1887F",
    "cHighlight": "F48FB1",
    "cHomework": "F48FB1",
    "cInfolineBg": "A1887F",
    "cInfolineText": "FFFFFF",
    "dpDividerWidth": 1.0,
    "dpHighlightWidth": 2.0,
    "dpHomework": 5.0,
    "dpPaddingBottom": 3.0,
    "dpPaddingLeft": 3.0,
    "dpPaddingRight": 3.0,
    "dpPaddingTop": 3.0,
    "dpTextPadding": 2.0,
    "spInfolineTextSize": 12.0,
    "spPrimaryText": 18.0,
    "spSecondaryText": 12.0
}